watson/__init__.py
watson/auth/__init__.py
watson/auth/authorization.py
watson/auth/commands.py
watson/auth/config.py
watson/auth/crypto.py
watson/auth/forms.py
watson/auth/listeners.py
watson/auth/managers.py
watson/auth/models.py
watson/auth/panels.py
watson/auth/validators.py
watson/auth/providers/__init__.py
watson/auth/providers/abc.py
watson/auth/providers/exceptions.py
watson/auth/providers/jwt/__init__.py
watson/auth/providers/jwt/decorators.py
watson/auth/providers/session/__init__.py
watson/auth/providers/session/decorators.py
watson/auth/views/auth/forgotten_password.html
watson/auth/views/auth/login.html
watson/auth/views/auth/reset_password.html
watson/auth/views/auth/emails/forgotten-password.html
watson/auth/views/auth/emails/reset-password.html
watson/auth/views/debug/panels/auth.html
watson/auth/views/errors/401.html
watson/auth/views/errors/403.html
watson_auth-4.0.1.dist-info/AUTHORS
watson_auth-4.0.1.dist-info/LICENSE
watson_auth-4.0.1.dist-info/METADATA
watson_auth-4.0.1.dist-info/WHEEL
watson_auth-4.0.1.dist-info/top_level.txt
watson_auth-4.0.1.dist-info/RECORD
