Metadata-Version: 2.1
Name: watson-auth
Version: 4.0.1
Summary: Authorization and authentication library for Watson.
Home-page: http://github.com/watsonpy/watson-auth
Author: Simon Coulton
Author-email: simon@bespohk.com
License: Copyright (c) Bespohk and individual contributors.
Requires-Dist: watson-db (>=2.4.0)
Requires-Dist: watson-validators (>=1.0.1)
Requires-Dist: watson-form (>=3.1.3)
Requires-Dist: watson-mail (>=1.0.0)
Requires-Dist: bcrypt (==3.1.2)
Requires-Dist: PyJWT (==1.5.2)
Provides-Extra: test
Requires-Dist: pytest ; extra == 'test'
Requires-Dist: pytest-cov ; extra == 'test'
Requires-Dist: coverage ; extra == 'test'
Requires-Dist: coveralls ; extra == 'test'
